feature/__init__.py
feature/base.py
feature/py.typed
feature/references.py
feature/sources.py
feature_conf-0.0.0.dist-info/LICENSE
feature_conf-0.0.0.dist-info/METADATA
feature_conf-0.0.0.dist-info/WHEEL
feature_conf-0.0.0.dist-info/top_level.txt
feature_conf-0.0.0.dist-info/RECORD
